viaduct/dao/__init__.py
viaduct/dao/client.py
viaduct/dao/examples.py
viaduct/dao/v1/dao_pb2.py
viaduct/dao/v1/dao_pb2.pyi
viaduct/dao/v1/dao_pb2_grpc.py
viaduct_dao-0.1.99.dist-info/METADATA
viaduct_dao-0.1.99.dist-info/WHEEL
viaduct_dao-0.1.99.dist-info/licenses/LICENSE
viaduct_dao-0.1.99.dist-info/RECORD
