Metadata-Version: 2.3
Name: viaduct-dao
Version: 0.1.99
Summary: python dao client
Author-email: John Pugliesi <john@viaduct.ai>
License-File: LICENSE
Requires-Python: >=3.9
Requires-Dist: grpcio-tools<1.63,>=1.62
Requires-Dist: grpcio>=1.66
Requires-Dist: httpx>=0.25
Requires-Dist: mypy-protobuf>=3.6.0
Requires-Dist: protobuf>=4.25
Requires-Dist: types-protobuf~=5.27
